stream_recorder/__main__.py
stream_recorder/checker/channels.py
stream_recorder/checker/etc.py
stream_recorder/checker/main.py
stream_recorder/checker/timeout.py
stream_recorder/core/common.py
stream_recorder/core/config.py
stream_recorder/recorder/recorder.py
stream_recorder-25.0.4.dist-info/METADATA
stream_recorder-25.0.4.dist-info/WHEEL
stream_recorder-25.0.4.dist-info/entry_points.txt
stream_recorder-25.0.4.dist-info/top_level.txt
stream_recorder-25.0.4.dist-info/RECORD
