Metadata-Version: 2.4
Name: stream_recorder
Version: 25.0.4
License-Expression: GPL-3.0-only
Project-URL: repo, https://github.com/gmankab/stream_recorder
Requires-Python: >=3.10
Requires-Dist: yt_dlp
Requires-Dist: rich
Provides-Extra: build
Requires-Dist: setuptools; extra == "build"
Requires-Dist: twine; extra == "build"
Requires-Dist: build; extra == "build"
